<annotation>
	<folder>DATASET - Recortado</folder>
	<filename>101_0495.JPG</filename>
	<path>E:\TEETH-RECOGNITION-WITH-MACHINE-LEARNING\DATASET - Recortado\101_0495.JPG</path>
	<source>
		<database>Unknown</database>
	</source>
	<size>
		<width>2517</width>
		<height>1329</height>
		<depth>3</depth>
	</size>
	<segmented>0</segmented>
	<object>
		<name>boca</name>
		<pose>Unspecified</pose>
		<truncated>0</truncated>
		<difficult>0</difficult>
		<bndbox>
			<xmin>284</xmin>
			<ymin>444</ymin>
			<xmax>2162</xmax>
			<ymax>1064</ymax>
		</bndbox>
	</object>
</annotation>
