<annotation>
	<folder>DATASET - Recortado</folder>
	<filename>101_1025.JPG</filename>
	<path>E:\TEETH-RECOGNITION-WITH-MACHINE-LEARNING\DATASET - Recortado\101_1025.JPG</path>
	<source>
		<database>Unknown</database>
	</source>
	<size>
		<width>897</width>
		<height>457</height>
		<depth>3</depth>
	</size>
	<segmented>0</segmented>
	<object>
		<name>boca</name>
		<pose>Unspecified</pose>
		<truncated>0</truncated>
		<difficult>0</difficult>
		<bndbox>
			<xmin>37</xmin>
			<ymin>58</ymin>
			<xmax>836</xmax>
			<ymax>362</ymax>
		</bndbox>
	</object>
</annotation>
